fraudar/__init__.py
fraudar/export/MinTree.py
fraudar/export/README
fraudar/export/__init__.py
fraudar/export/greedy.py
fraudar/graph.py
fraudar/py.typed
rgmining_fraudar-0.7.6.dist-info/METADATA
rgmining_fraudar-0.7.6.dist-info/WHEEL
rgmining_fraudar-0.7.6.dist-info/licenses/COPYING
rgmining_fraudar-0.7.6.dist-info/licenses/LICENSE-2.0
rgmining_fraudar-0.7.6.dist-info/RECORD
