Metadata-Version: 2.4
Name: rgmining-fraudar
Version: 0.7.6
Summary: A wrapper of Fraudar algorithm for Review graph mining project
License-Expression: GPL-3.0-only
License-File: COPYING
License-File: LICENSE-2.0
Keywords: algorithm,fraudar,graph,kdd,mining,review
Author: Junpei Kawamoto
Author-email: kawamoto.junpei@gmail.com
Requires-Python: >=3.11
Classifier: Development Status :: 4 - Beta
Classifier: Intended Audience :: Science/Research
Classifier: License :: OSI Approved :: GNU General Public License v3 (GPLv3)
Classifier: Natural Language :: English
Classifier: Programming Language :: Python
Classifier: Programming Language :: Python :: 3 :: Only
Classifier: Programming Language :: Python :: 3.11
Classifier: Programming Language :: Python :: 3.12
Classifier: Programming Language :: Python :: 3.13
Classifier: Programming Language :: Python :: 3.14
Classifier: Topic :: Scientific/Engineering :: Information Analysis
Classifier: Topic :: Software Development :: Libraries
Provides-Extra: sample
Requires-Dist: click (>=8) ; extra == "sample"
Requires-Dist: numpy (>=2.2)
Requires-Dist: rgmining-synthetic-dataset (>=0.9) ; extra == "sample"
Requires-Dist: scikit-learn (>=1.6.1)
Project-URL: Documentation, https://rgmining.github.io/fraudar/
Project-URL: Homepage, https://rgmining.github.io/fraudar/
Project-URL: Repository, https://github.com/rgmining/fraudar
